setup.py
newpipv3/__init__.py
newpipv3.egg-info/PKG-INFO
newpipv3.egg-info/SOURCES.txt
newpipv3.egg-info/dependency_links.txt
newpipv3.egg-info/top_level.txt